recurdyn/AutoDesign.py
recurdyn/BNP.py
recurdyn/Chain.py
recurdyn/Chart.py
recurdyn/Control.py
recurdyn/DriveTrain.py
recurdyn/Durability.py
recurdyn/EHD.py
recurdyn/External.py
recurdyn/ExternalSPI.py
recurdyn/FFlex.py
recurdyn/FlexInterface.py
recurdyn/Flexible.py
recurdyn/MMS.py
recurdyn/MTT2D.py
recurdyn/MTT3D.py
recurdyn/Post.py
recurdyn/PostAnalysis.py
recurdyn/ProcessNet.py
recurdyn/R2R2D.py
recurdyn/RFlex.py
recurdyn/RecurDyn.py
recurdyn/Tire.py
recurdyn/ToolkitCommon.py
recurdyn/TrackHM.py
recurdyn/TrackLM.py
recurdyn/__init__.py
recurdyn/color.py
recurdyn/common_func.py
recurdyn/utils/color.py
recurdyn/utils/rplt.py
recurdyn-10.1.1.41607.dist-info/LICENSE.txt
recurdyn-10.1.1.41607.dist-info/METADATA
recurdyn-10.1.1.41607.dist-info/WHEEL
recurdyn-10.1.1.41607.dist-info/top_level.txt
recurdyn-10.1.1.41607.dist-info/RECORD
