Metadata-Version: 2.1
Name: recurdyn
Version: 10.1.1.41607
Summary: RecurDyn 2023 SP1
Author: FunctionBay, Inc
Author-email: FBHQ_GUI@functionbay.co.kr
License: Copyright (c) 2018 The Python Packaging Authority
Project-URL: homepage, https://functionbay.com
Keywords: recurdyn,dynamics,engineering
Classifier: Programming Language :: Python :: 3
Classifier: License :: OSI Approved :: MIT License
Classifier: Operating System :: Microsoft :: Windows
Requires-Python: >=3.5
License-File: LICENSE.txt
Requires-Dist: pywin32
